<?xml version="1.0" encoding="UTF-8"?>
<song>
  <title>059 Mirad qué amor</title>
  <author>1 Juan 3:1</author>
  <copyright></copyright>
  <hymn_number></hymn_number>
  <presentation></presentation>
  <ccli></ccli>
  <capo print="false"></capo>
  <key></key>
  <aka></aka>
  <key_line></key_line>
  <user1></user1>
  <user2></user2>
  <user3></user3>
  <theme></theme>
  <tempo></tempo>
  <time_sig></time_sig>
  <lyrics> 
 Mirad qué amor nos ha dado el Padre
.
 al hacernos hijos de Dios;
.
 mirad qué amor nos ha dado el Padre
.
 al hacernos hijos de Dios;
.
 para ser llamados hijos de Dios;
.
 para ser llamados hijos de Dios. ||
.
 Mirad qué amor nos ha dado el Padre
.
 al hacernos hijos de Dios;
.
 mirad qué amor nos ha dado el Padre
.
 al hacernos hijos de Dios.</lyrics></song>