<?xml version="1.0" encoding="UTF-8"?>
<song>
  <title>120 ¡Cuánto me alegra!</title>
  <author></author>
  <copyright></copyright>
  <hymn_number></hymn_number>
  <presentation>V1 C V2 C V3 C</presentation>
  <ccli></ccli>
  <capo print="false"></capo>
  <key></key>
  <aka></aka>
  <key_line></key_line>
  <user1></user1>
  <user2></user2>
  <user3></user3>
  <theme></theme>
  <tempo></tempo>
  <time_sig></time_sig>
  <lyrics>[V1]
 ¡Cuánto me alegra que nuestro Señor
 diera su vida por el pecador!
 Hizo sin par maravillas aquí,
 y la más grande es que me ama a mí.
 
[C]
 
 ¡Qué maravilla! Me ama Jesús,
 me ama Jesús, me ama Jesús.
 ¡Qué maravilla! Me ama Jesús;
 sí, me ama aún a mí.
 
[V2]
 Aunque vagaba olvidándome de él,
 él me siguió porque siempre es fiel;
 presto a sus brazos amantes volví
 al recordar que Jesús me ama a mí.
 
[V3]
 Cuando en el cielo ver pueda a Jesús,
 ya revestido de gloriosa luz,
 entonaré mi himno eterno allí:
 “¡Qué maravilla! ¡Jesús me ama a mí!”</lyrics></song>