<?xml version="1.0" encoding="UTF-8"?>
<song>
  <title>155 En Sion Jesús hoy reina</title>
  <author></author>
  <copyright></copyright>
  <hymn_number></hymn_number>
  <presentation>V1 V2 V3 </presentation>
  <ccli></ccli>
  <capo print="false"></capo>
  <key></key>
  <aka></aka>
  <key_line></key_line>
  <user1></user1>
  <user2></user2>
  <user3></user3>
  <theme></theme>
  <tempo></tempo>
  <time_sig></time_sig>
  <lyrics>[V1]
 En Sion Jesús hoy reina, alégrate, mortal,
 y ve con devoción y fe al trono celestial.
 En Sion Jesús hoy reina en gloria y majestad,
 venid, oh poderosos, y su gloria proclamad.
 
[V2]
 En Sion Jesús hoy reina cual infinito ser,
 los mares y abismos él gobierna con poder.
 ¡Oh, todo el universo alabe al Salvador!
 Proclámenle los pueblos cual amante Redentor.
 
[V3]
 
 En Sion Jesús hoy reina, del orbe es regidor.
 ¡Venid con regocijo y adoradle con fervor!
 y ante su grandeza venid con santa unción.
 Venid y coronadle Rey con toda devoción.</lyrics></song>