<?xml version="1.0" encoding="UTF-8"?>
<song>
  <title>197 Dulce Espíritu</title>
  <author></author>
  <copyright></copyright>
  <hymn_number></hymn_number>
  <presentation></presentation>
  <ccli></ccli>
  <capo print="false"></capo>
  <key></key>
  <aka></aka>
  <key_line></key_line>
  <user1></user1>
  <user2></user2>
  <user3></user3>
  <theme></theme>
  <tempo></tempo>
  <time_sig></time_sig>
  <lyrics>. tono \F ritmo 4/4
[V1]
 
.       E.               E. Bm. C#7.
 Hay un dulce Espíritu aquí,
.     A.             B7.             E.   A.
 y yo sé que es el Espíritu de mi Señor.
.       E.                 E. Bm. C#7.
 En los rostros veo gozo y paz,
.     A              B7          E.
 y yo sé que está presente el Señor. ||
 
.E.    A. E.      E.   A.  E.
 Dulce presencia del Salvador;
.     Ab7.   C#m. 
 permanece aquí, Señor,
. F#7.             B7.
 llénanos con tu amor.||
.E.      A. E.       E. Ab7.   C#m. 
 Por tus bondades te adoramos hoy;
.F#7.       E.       C#m.          E.      C#m.
 y que al salir de aquí, con nueva vida en ti,
.   F#7.  B7.  E.
 llevemos tu amor.</lyrics></song>