<?xml version="1.0" encoding="UTF-8"?>
<song>
  <title>286 Hay una fuente sin igual</title>
  <author>Zacarías 13:1</author>
  <copyright></copyright>
  <hymn_number></hymn_number>
  <presentation>V1 V2 V3 V4</presentation>
  <ccli></ccli>
  <capo print="false"></capo>
  <key>A</key>
  <aka></aka>
  <key_line></key_line>
  <user1></user1>
  <user2></user2>
  <user3></user3>
  <theme></theme>
  <tempo></tempo>
  <time_sig></time_sig>
  <lyrics>.Tono: SIb Ritmo: 4/4
 
[V1]
.    A.          D.   A.                     E.
 Hay una fuente sin igual, la sangre de Emanuel,
.   A.         D.    A.                E.       A.
 en donde lava cada cual las manchas que hay en él,
.                       D.       A.                E.
 las manchas que hay en él, las manchas que hay en él;
.   A.    A7.  D.   A.       E.         E7.     A.
 en donde lava cada cual las manchas que hay en él.
 
[V2]
 
 El malhechor se convirtió muriendo en una cruz,
 al ver la sangre que vertió sin culpa el buen Jesús,
 sin culpa el buen Jesús, sin culpa el buen Jesús;
 al ver la sangre que vertió sin culpa el buen Jesús.
 
[V3]
 Y yo también, cuan malo soy, lavarme allí podré;
 y en tanto que en el mundo estoy su gloria cantaré,
 su gloria cantaré, su gloria cantaré;
 y en tanto que en el mundo estoy su gloria cantaré.
 
[V4]
 Y cuando del sepulcro ya resucitado esté,
 canción más noble y dulce allá en gloria entonaré,
 en gloria entonaré, en gloria entonaré;
 canción más nombre y dulce allá en gloria entonaré.</lyrics></song>