<?xml version="1.0" encoding="UTF-8"?>
<song>
  <title>447 Más santidad dame</title>
  <author></author>
  <copyright></copyright>
  <hymn_number></hymn_number>
  <presentation>V1 V2 V3</presentation>
  <ccli></ccli>
  <capo print="false"></capo>
  <key></key>
  <aka></aka>
  <key_line></key_line>
  <user1></user1>
  <user2></user2>
  <user3></user3>
  <theme></theme>
  <tempo></tempo>
  <time_sig></time_sig>
  <lyrics>[V1]
 Más santidad dame, más odio al mal,
 más calma en las penas, más alto ideal;
 más fe en el Maestro, más consagración,
 más celo en servirle, más fe en la oración.
 
[V2]
 
 Más prudente hazme, más sabio en él,
 más firme en su causa, más fuerte y más fiel;
 más recto en la vida, más triste al pecar,
 más humilde hijo, más pronto en amar.
 
[V3]
 Más pureza dame, más fuerza en Jesús;
 más de su dominio, más paz en la cruz;
 más rica esperanza, más obras aquí,
 más ansia del cielo, más gozo allí.</lyrics></song>