<?xml version="1.0" encoding="UTF-8"?>
<song>
  <title>574 Testimonio</title>
  <author></author>
  <copyright></copyright>
  <hymn_number></hymn_number>
  <presentation>V1 V2 V3 </presentation>
  <ccli></ccli>
  <capo print="false"></capo>
  <key></key>
  <aka></aka>
  <key_line></key_line>
  <user1></user1>
  <user2></user2>
  <user3></user3>
  <theme></theme>
  <tempo></tempo>
  <time_sig></time_sig>
  <lyrics>. tono \Eb ritmo 4/4
 
[V1]
.D.     
 En mi vivir voy a decir que Cristo
.
 murió por mí en la cruz y me salvó.
.
 En mi vivir voy a decir que Cristo
.
 me prometió que pronto volverá. |||
.
 Al cantar lleno de felicidad,
.
 mi vivir mostrará quién es Jesús.
.
 Al cantar lleno de felicidad,
.
 quiero ser la razón de vida y luz.
 
[V2]
 En mi hablar voy a contar que Cristo
 murió por mí en la cruz y me salvó.
 En mi hablar voy a contar que Cristo
 me prometió que pronto volverá.|||
 Al cantar lleno de felicidad,
 mi hablar contará quién es Jesús.
 Al cantar lleno de felicidad,
 quiero ser la razón de vida y luz.
 
[V3]
 En mi reír voy a mostrar que Cristo
 murió por mí en la cruz y me salvó.
 En mi reír vaya mostrar que Cristo
 me prometió que pronto volverá.|||
 Al cantar lleno de felicidad,
 mi reír mostrará quién es Jesús.
 Al cantar lleno de felicidad,
 quiero ser la razón de vida y luz.</lyrics></song>